pyautoproxy/__init__.py
pyautoproxy/main.py
pyautoproxy-0.0.15.dist-info/METADATA
pyautoproxy-0.0.15.dist-info/WHEEL
pyautoproxy-0.0.15.dist-info/entry_points.txt
pyautoproxy-0.0.15.dist-info/top_level.txt
pyautoproxy-0.0.15.dist-info/RECORD
