Metadata-Version: 2.1
Name: pyautoproxy
Version: 0.0.15
Summary: Light weight auto proxy server
Home-page: https://github.com/yamsergey/pyautoproxy
Author: Sergey Yamshchikov
Author-email: yamsergey@gmail.com
License: UNKNOWN
Platform: UNKNOWN
Classifier: Programming Language :: Python :: 3
Classifier: License :: OSI Approved :: MIT License
Classifier: Operating System :: OS Independent
Requires-Python: >=3.6
